DeStringCare/AESCipher.py
DeStringCare/__init__.py
DeStringCare/destringcare.py
DeStringCare/other_secrets.txt
DeStringCare-0.0.5.dist-info/METADATA
DeStringCare-0.0.5.dist-info/WHEEL
DeStringCare-0.0.5.dist-info/entry_points.txt
DeStringCare-0.0.5.dist-info/top_level.txt
DeStringCare-0.0.5.dist-info/RECORD
