Metadata-Version: 2.1
Name: DeStringCare
Version: 0.0.5
Summary: DeStringCare for extracting Android apk secrets
Home-page: https://github.com/DainisGorbunovs/DeStringCare
Author: Dainis Gorbunovs
Author-email: dgdev@protonmail.com
License: UNKNOWN
Keywords: StringCare,destringcare,decrypt,apk,secrets
Platform: UNKNOWN
Classifier: Intended Audience :: Developers
Classifier: License :: OSI Approved :: MIT License
Classifier: Operating System :: OS Independent
Classifier: Programming Language :: Python :: 3
Classifier: Programming Language :: Python :: 3.4
Classifier: Programming Language :: Python :: 3.5
Classifier: Programming Language :: Python :: 3.6
Classifier: Programming Language :: Python :: 3.7
Classifier: Development Status :: 5 - Production/Stable
Classifier: Topic :: Software Development :: Libraries :: Python Modules
Requires-Dist: cryptography
Requires-Dist: pycryptodomex
Requires-Dist: pyOpenSSL
Requires-Dist: pyjks
Requires-Dist: pyaxmlparser
